cf_check_apps.py
setup.py
cf_check_apps.egg-info/PKG-INFO
cf_check_apps.egg-info/SOURCES.txt
cf_check_apps.egg-info/dependency_links.txt
cf_check_apps.egg-info/entry_points.txt
cf_check_apps.egg-info/not-zip-safe
cf_check_apps.egg-info/requires.txt
cf_check_apps.egg-info/top_level.txt