Metadata-Version: 1.0
Name: cf-check-apps
Version: 1.1
Summary: Check the status of your CloudFoundry apps
Home-page: https://github.com/ojii/cf-check-apps
Author: Jonas Obrist
Author-email: ojiidotch@gmail.com
License: BSD
Platform: OS Independent
